smart_fit/__init__.py
smart_fit/smart_fit.py
smart_fit-0.0.8.dist-info/LICENSE
smart_fit-0.0.8.dist-info/METADATA
smart_fit-0.0.8.dist-info/WHEEL
smart_fit-0.0.8.dist-info/top_level.txt
smart_fit-0.0.8.dist-info/RECORD
